vecstore/__init__.py
vecstore/__init__.pyi
vecstore/vecstore.cpython-313-darwin.so
vecstore_rs-1.0.0.dist-info/METADATA
vecstore_rs-1.0.0.dist-info/WHEEL
vecstore_rs-1.0.0.dist-info/licenses/LICENSE
vecstore_rs-1.0.0.dist-info/RECORD
