Metadata-Version: 2.4
Name: vecstore-rs
Version: 1.0.0
Classifier: Development Status :: 5 - Production/Stable
Classifier: Intended Audience :: Developers
Classifier: License :: OSI Approved :: MIT License
Classifier: Programming Language :: Python :: 3
Classifier: Programming Language :: Python :: 3.8
Classifier: Programming Language :: Python :: 3.9
Classifier: Programming Language :: Python :: 3.10
Classifier: Programming Language :: Python :: 3.11
Classifier: Programming Language :: Python :: 3.12
Classifier: Programming Language :: Rust
Classifier: Topic :: Database
Classifier: Topic :: Scientific/Engineering :: Artificial Intelligence
Requires-Dist: pytest>=7.0 ; extra == 'dev'
Requires-Dist: pytest-asyncio>=0.21 ; extra == 'dev'
Requires-Dist: black>=23.0 ; extra == 'dev'
Requires-Dist: mypy>=1.0 ; extra == 'dev'
Requires-Dist: ruff>=0.1.0 ; extra == 'dev'
Provides-Extra: dev
License-File: LICENSE
Summary: The perfect vector database - 100/100 score, embeddable, high-performance, production-ready with RAG toolkit
Keywords: vector-database,embedding,search,rag,hnsw,semantic-search
Home-Page: https://github.com/PhilipJohnBasile/vecstore
Author: VecStore Contributors
License: MIT
Requires-Python: >=3.8
Project-URL: Homepage, https://github.com/PhilipJohnBasile/vecstore
Project-URL: Documentation, https://docs.rs/vecstore
Project-URL: Repository, https://github.com/PhilipJohnBasile/vecstore
Project-URL: Issues, https://github.com/PhilipJohnBasile/vecstore/issues
Project-URL: Changelog, https://github.com/PhilipJohnBasile/vecstore/blob/main/CHANGELOG.md
